genetok/__init__.py
genetok/genepool.py
genetok/layers.py
genetok/tokenizer.py
genetok-0.1.12.dist-info/METADATA
genetok-0.1.12.dist-info/WHEEL
genetok-0.1.12.dist-info/top_level.txt
genetok-0.1.12.dist-info/RECORD
