Metadata-Version: 2.1
Name: genetok
Version: 0.1.12
Summary: A Genetic Algorithm Tokenizer
Home-page: https://github.com/dadukhankevin/genetok
Author: Daniel Losey
Author-email: danieljlosey@gmail.com
Requires-Python: >=3.6
Requires-Dist: finch-genetics
